<?xml version="1.0" encoding="utf-8" ?>
<dwsync>
<file name="config.php" server="ftp.geniusbydesign.co.uk//public_html/sites/elementsexhibition/" local="129959867361960631" remote="130011732600000000" Dst="1" />
<file name="autoload.php" server="ftp.geniusbydesign.co.uk//public_html/sites/elementsexhibition/" local="129968585512186573" remote="130011732600000000" Dst="1" />
<file name="constants.php" server="ftp.geniusbydesign.co.uk//public_html/sites/elementsexhibition/" local="129941795120000000" remote="130011732600000000" Dst="1" />
<file name="database.php" server="ftp.geniusbydesign.co.uk//public_html/sites/elementsexhibition/" local="129941795120000000" remote="130011732600000000" Dst="1" />
<file name="doctypes.php" server="ftp.geniusbydesign.co.uk//public_html/sites/elementsexhibition/" local="129941795120000000" remote="130011732600000000" Dst="1" />
<file name="foreign_chars.php" server="ftp.geniusbydesign.co.uk//public_html/sites/elementsexhibition/" local="129941795120000000" remote="130011732600000000" Dst="1" />
<file name="hooks.php" server="ftp.geniusbydesign.co.uk//public_html/sites/elementsexhibition/" local="129941795120000000" remote="130011732600000000" Dst="1" />
<file name="index.html" server="ftp.geniusbydesign.co.uk//public_html/sites/elementsexhibition/" local="129664507580000000" remote="130011732600000000" Dst="1" />
<file name="migration.php" server="ftp.geniusbydesign.co.uk//public_html/sites/elementsexhibition/" local="129941795120000000" remote="130011732600000000" Dst="1" />
<file name="mimes.php" server="ftp.geniusbydesign.co.uk//public_html/sites/elementsexhibition/" local="129941795120000000" remote="130011732600000000" Dst="1" />
<file name="profiler.php" server="ftp.geniusbydesign.co.uk//public_html/sites/elementsexhibition/" local="129941795120000000" remote="130011732600000000" Dst="1" />
<file name="routes.php" server="ftp.geniusbydesign.co.uk//public_html/sites/elementsexhibition/" local="129956707589849569" remote="130011732600000000" Dst="1" />
<file name="smileys.php" server="ftp.geniusbydesign.co.uk//public_html/sites/elementsexhibition/" local="129941795120000000" remote="130011732600000000" Dst="1" />
<file name="user_agents.php" server="ftp.geniusbydesign.co.uk//public_html/sites/elementsexhibition/" local="129941795120000000" remote="130011732600000000" Dst="1" />
</dwsync>